encode_dataframe/__init__.py
encode_dataframe-0.1.dist-info/DESCRIPTION.rst
encode_dataframe-0.1.dist-info/top_level.txt
encode_dataframe-0.1.dist-info/METADATA
encode_dataframe-0.1.dist-info/metadata.json
encode_dataframe-0.1.dist-info/WHEEL
encode_dataframe-0.1.dist-info/RECORD
