Metadata-Version: 2.0
Name: encode-dataframe
Version: 0.1
Summary: Convert UCSC's ENCODE metadata into pandas DataFrames
Home-page: UNKNOWN
Author: Ryan Dale
Author-email: dalerr@niddk.nih.gov
License: MIT
Platform: UNKNOWN
Requires-Dist: pandas
